pepsi/__init__.py
pepsi/__main__.py
pepsi/calculator.py
pepsi/constants.py
pepsi/features.py
pepsi/plots.py
pepsi/utils.py
thesis_pepsi_package-0.1.0.dist-info/licenses/LICENSE
thesis_pepsi_package-0.1.0.dist-info/METADATA
thesis_pepsi_package-0.1.0.dist-info/WHEEL
thesis_pepsi_package-0.1.0.dist-info/entry_points.txt
thesis_pepsi_package-0.1.0.dist-info/top_level.txt
thesis_pepsi_package-0.1.0.dist-info/RECORD
