Metadata-Version: 2.4
Name: thesis-pepsi-package
Version: 0.1.0
Summary: A package to calculate peptide features.
Author-email: Ronja Krueger <ronja.krueger@student.hpi.de>
License-Expression: MIT
Project-URL: Repository, https://github.com/ronjakrg/thesis-pepsi-package
Project-URL: Issues, https://github.com/ronjakrg/thesis-pepsi-package/issues
Keywords: peptide,proteomics
Classifier: Programming Language :: Python :: 3
Classifier: Operating System :: OS Independent
Requires-Python: >=3.11
License-File: LICENSE
Dynamic: license-file
